surfaces/__init__.py
surfaces/_array_utils.py
surfaces/_visualize.py
surfaces/py.typed
surfaces/_surrogates/__init__.py
surfaces/_surrogates/_ml_registry.py
surfaces/_surrogates/_ml_surrogate_trainer.py
surfaces/_surrogates/_onnx_utils.py
surfaces/_surrogates/_surrogate_loader.py
surfaces/_surrogates/_surrogate_trainer.py
surfaces/_surrogates/_surrogate_validator.py
surfaces/_surrogates/_dashboard/__init__.py
surfaces/_surrogates/_dashboard/__main__.py
surfaces/_surrogates/_dashboard/app.py
surfaces/_surrogates/_dashboard/database.py
surfaces/_surrogates/_dashboard/sync.py
surfaces/_surrogates/_dashboard/training.py
surfaces/_surrogates/_dashboard/validation.py
surfaces/_surrogates/_dashboard/_pages/__init__.py
surfaces/_surrogates/_dashboard/_pages/details.py
surfaces/_surrogates/_dashboard/_pages/overview.py
surfaces/_surrogates/_dashboard/_pages/training.py
surfaces/_surrogates/_dashboard/_pages/validation.py
surfaces/collection/__init__.py
surfaces/collection/collection.py
surfaces/collection/singleton.py
surfaces/collection/suites.py
surfaces/collection/utils.py
surfaces/custom_test_function/__init__.py
surfaces/custom_test_function/_custom_test_function.py
surfaces/custom_test_function/_namespaces/__init__.py
surfaces/custom_test_function/_namespaces/_analysis.py
surfaces/custom_test_function/_namespaces/_plot.py
surfaces/custom_test_function/_namespaces/_storage.py
surfaces/custom_test_function/_namespaces/_surrogate.py
surfaces/custom_test_function/storage/__init__.py
surfaces/custom_test_function/storage/_memory.py
surfaces/custom_test_function/storage/_protocol.py
surfaces/custom_test_function/storage/_sqlite.py
surfaces/modifiers/__init__.py
surfaces/modifiers/_base_modifier.py
surfaces/modifiers/_delay.py
surfaces/modifiers/noise/__init__.py
surfaces/modifiers/noise/_base.py
surfaces/modifiers/noise/_gaussian.py
surfaces/modifiers/noise/_multiplicative.py
surfaces/modifiers/noise/_uniform.py
surfaces/test_functions/__init__.py
surfaces-0.7.1.dist-info/licenses/LICENSE
surfaces-0.7.1.dist-info/METADATA
surfaces-0.7.1.dist-info/WHEEL
surfaces-0.7.1.dist-info/entry_points.txt
surfaces-0.7.1.dist-info/top_level.txt
surfaces-0.7.1.dist-info/RECORD
