Metadata-Version: 2.4
Name: surfaces
Version: 0.7.1
Summary: A collection and visualization of black-box objective functions
Author-email: Simon Blanke <simon.blanke@yahoo.com>
Maintainer-email: Simon Blanke <simon.blanke@yahoo.com>
License-Expression: MIT
Project-URL: Homepage, https://github.com/SimonBlanke/Surfaces
Project-URL: Bug Reports, https://github.com/SimonBlanke/Surfaces/issues
Project-URL: Source, https://github.com/SimonBlanke/Surfaces/
Keywords: test-functions,optimization,gradient-free-optimization,visualization,data-science,cec,bbob,machine-learning,surrogate-models
Classifier: Programming Language :: Python :: 3
Classifier: Programming Language :: Python :: 3.10
Classifier: Programming Language :: Python :: 3.11
Classifier: Programming Language :: Python :: 3.12
Classifier: Programming Language :: Python :: 3.13
Classifier: Programming Language :: Python :: 3.14
Classifier: Operating System :: OS Independent
Classifier: Topic :: Scientific/Engineering :: Information Analysis
Classifier: Topic :: Scientific/Engineering :: Mathematics
Classifier: Topic :: Software Development :: Libraries :: Python Modules
Classifier: Intended Audience :: Developers
Classifier: Intended Audience :: Information Technology
Classifier: Intended Audience :: Science/Research
Requires-Python: >=3.10
License-File: LICENSE
Requires-Dist: numpy>=1.18.1
Provides-Extra: viz
Requires-Dist: matplotlib; extra == "viz"
Requires-Dist: plotly; extra == "viz"
Provides-Extra: ml
Requires-Dist: scikit-learn; extra == "ml"
Provides-Extra: cec
Requires-Dist: surfaces-cec-data==0.0.1; extra == "cec"
Provides-Extra: timeseries
Requires-Dist: surfaces[ml]; extra == "timeseries"
Requires-Dist: sktime>=0.24.0; extra == "timeseries"
Provides-Extra: images
Requires-Dist: surfaces[ml]; extra == "images"
Requires-Dist: tensorflow>=2.10.0; extra == "images"
Provides-Extra: xgboost
Requires-Dist: surfaces[ml]; extra == "xgboost"
Requires-Dist: xgboost>=1.7.0; extra == "xgboost"
Provides-Extra: surrogates
Requires-Dist: surfaces-onnx-files==0.0.1; extra == "surrogates"
Requires-Dist: onnxruntime>=1.10.0; extra == "surrogates"
Provides-Extra: full
Requires-Dist: surfaces[cec,images,ml,surrogates,timeseries,viz,xgboost]; extra == "full"
Provides-Extra: dev
Requires-Dist: surfaces[full]; extra == "dev"
Requires-Dist: ruff; extra == "dev"
Requires-Dist: pre-commit; extra == "dev"
Requires-Dist: check-manifest; extra == "dev"
Provides-Extra: test
Requires-Dist: surfaces[full]; extra == "test"
Requires-Dist: pytest>=7.0.0; extra == "test"
Requires-Dist: pytest-cov; extra == "test"
Requires-Dist: ruff; extra == "test"
Requires-Dist: gradient-free-optimizers; extra == "test"
Provides-Extra: test-minimal
Requires-Dist: pytest>=7.0.0; extra == "test-minimal"
Requires-Dist: pytest-cov; extra == "test-minimal"
Provides-Extra: build
Requires-Dist: build; extra == "build"
Provides-Extra: surrogate
Requires-Dist: onnxruntime>=1.16.0; extra == "surrogate"
Provides-Extra: surrogate-train
Requires-Dist: onnxruntime>=1.16.0; extra == "surrogate-train"
Requires-Dist: skl2onnx>=1.16.0; extra == "surrogate-train"
Provides-Extra: dashboard
Requires-Dist: surfaces[ml,surrogate-train]; extra == "dashboard"
Requires-Dist: streamlit>=1.28.0; extra == "dashboard"
Requires-Dist: plotly>=5.0.0; extra == "dashboard"
Requires-Dist: pandas>=1.3.0; extra == "dashboard"
Dynamic: license-file
